redisenv/__main__.py
redisenv/commands/__init__.py
redisenv/commands/cluster.py
redisenv/commands/enterprise.py
redisenv/commands/replica.py
redisenv/commands/sentinel.py
redisenv/commands/standalone.py
redisenv/composer.py
redisenv/env.py
redisenv/templates/cluster.conf.tmpl
redisenv/templates/cluster.tmpl
redisenv/templates/enterprise.tmpl
redisenv/templates/replica.tmpl
redisenv/templates/sentinel.conf.tmpl
redisenv/templates/sentinel.tmpl
redisenv/templates/standalone.tmpl
redisenv/templates/start_cluster.sh.tmpl
redisenv/util.py
redisenv-0.3.1.dist-info/LICENSE
redisenv-0.3.1.dist-info/METADATA
redisenv-0.3.1.dist-info/WHEEL
redisenv-0.3.1.dist-info/entry_points.txt
redisenv-0.3.1.dist-info/RECORD
